{
"meta":{"test_sets":[],"test_metrics":[],"learn_metrics":[{"best_value":"Min","name":"RMSE"}],"launch_mode":"Train","parameters":"","iteration_count":100,"learn_sets":["learn"],"name":"experiment"},
"iterations":[
{"learn":[14.005006],"iteration":0,"passed_time":0.001933217324,"remaining_time":0.1913885151},
{"learn":[13.14441192],"iteration":1,"passed_time":0.003917505669,"remaining_time":0.1919577778},
{"learn":[12.34258257],"iteration":2,"passed_time":0.005709796768,"remaining_time":0.1846167622},
{"learn":[11.64527793],"iteration":3,"passed_time":0.007468095036,"remaining_time":0.1792342809},
{"learn":[11.02766183],"iteration":4,"passed_time":0.009315580693,"remaining_time":0.1769960332},
{"learn":[10.43485794],"iteration":5,"passed_time":0.01127267341,"remaining_time":0.1766052168},
{"learn":[9.890641275],"iteration":6,"passed_time":0.0136076164,"remaining_time":0.1807869036},
{"learn":[9.492161212],"iteration":7,"passed_time":0.01549993386,"remaining_time":0.1782492393},
{"learn":[9.105082953],"iteration":8,"passed_time":0.01775139274,"remaining_time":0.1794863044},
{"learn":[8.674157135],"iteration":9,"passed_time":0.01969079076,"remaining_time":0.1772171169},
{"learn":[8.341743544],"iteration":10,"passed_time":0.02185463679,"remaining_time":0.1768238795},
{"learn":[8.049372916],"iteration":11,"passed_time":0.02360684977,"remaining_time":0.1731168983},
{"learn":[7.757318612],"iteration":12,"passed_time":0.02515860677,"remaining_time":0.1683691376},
{"learn":[7.522206899],"iteration":13,"passed_time":0.02677468246,"remaining_time":0.1644730494},
{"learn":[7.297756655],"iteration":14,"passed_time":0.02903648126,"remaining_time":0.1645400605},
{"learn":[7.088359431],"iteration":15,"passed_time":0.03091700973,"remaining_time":0.1623143011},
{"learn":[6.882113791],"iteration":16,"passed_time":0.03337493011,"remaining_time":0.1629481882},
{"learn":[6.704728832],"iteration":17,"passed_time":0.03571482199,"remaining_time":0.1627008557},
{"learn":[6.563881962],"iteration":18,"passed_time":0.03811837677,"remaining_time":0.1625046589},
{"learn":[6.418790279],"iteration":19,"passed_time":0.03996221269,"remaining_time":0.1598488508},
{"learn":[6.315756953],"iteration":20,"passed_time":0.04176771218,"remaining_time":0.1571261553},
{"learn":[6.210157751],"iteration":21,"passed_time":0.04385990077,"remaining_time":0.1555032845},
{"learn":[6.115058449],"iteration":22,"passed_time":0.04582670326,"remaining_time":0.1534198327},
{"learn":[6.014819884],"iteration":23,"passed_time":0.04795848294,"remaining_time":0.1518685293},
{"learn":[5.93117229],"iteration":24,"passed_time":0.050047213,"remaining_time":0.150141639},
{"learn":[5.844857622],"iteration":25,"passed_time":0.05483409209,"remaining_time":0.1560662621},
{"learn":[5.771145213],"iteration":26,"passed_time":0.05733000818,"remaining_time":0.1550033555},
{"learn":[5.704018229],"iteration":27,"passed_time":0.06080727899,"remaining_time":0.1563615745},
{"learn":[5.665806474],"iteration":28,"passed_time":0.06287647605,"remaining_time":0.1539389586},
{"learn":[5.616500369],"iteration":29,"passed_time":0.06494977622,"remaining_time":0.1515494778},
{"learn":[5.558023666],"iteration":30,"passed_time":0.06691867074,"remaining_time":0.1489480091},
{"learn":[5.510080976],"iteration":31,"passed_time":0.06889768471,"remaining_time":0.14640758},
{"learn":[5.468747792],"iteration":32,"passed_time":0.07077676452,"remaining_time":0.1436982795},
{"learn":[5.429275534],"iteration":33,"passed_time":0.07285175666,"remaining_time":0.1414181159},
{"learn":[5.402117324],"iteration":34,"passed_time":0.07488265097,"remaining_time":0.1390677804},
{"learn":[5.367635151],"iteration":35,"passed_time":0.07700925127,"remaining_time":0.1369053356},
{"learn":[5.345181232],"iteration":36,"passed_time":0.07926562137,"remaining_time":0.1349657877},
{"learn":[5.319151269],"iteration":37,"passed_time":0.08107180069,"remaining_time":0.1322750432},
{"learn":[5.296134146],"iteration":38,"passed_time":0.0826857098,"remaining_time":0.1293289307},
{"learn":[5.269629003],"iteration":39,"passed_time":0.08437235744,"remaining_time":0.1265585362},
{"learn":[5.251147059],"iteration":40,"passed_time":0.08599566606,"remaining_time":0.1237498609},
{"learn":[5.248003302],"iteration":41,"passed_time":0.08681102302,"remaining_time":0.1198818889},
{"learn":[5.232376509],"iteration":42,"passed_time":0.08836806081,"remaining_time":0.1171390574},
{"learn":[5.213524255],"iteration":43,"passed_time":0.08996608906,"remaining_time":0.1145022952},
{"learn":[5.189691584],"iteration":44,"passed_time":0.09156957688,"remaining_time":0.1119183717},
{"learn":[5.166052198],"iteration":45,"passed_time":0.09357702871,"remaining_time":0.1098512946},
{"learn":[5.140406659],"iteration":46,"passed_time":0.09509622993,"remaining_time":0.1072361742},
{"learn":[5.118929684],"iteration":47,"passed_time":0.09687389203,"remaining_time":0.1049467164},
{"learn":[5.108792602],"iteration":48,"passed_time":0.09843992608,"remaining_time":0.1024578823},
{"learn":[5.098141225],"iteration":49,"passed_time":0.09982703299,"remaining_time":0.09982703299},
{"learn":[5.085926393],"iteration":50,"passed_time":0.1009453948,"remaining_time":0.09698675189},
{"learn":[5.067816804],"iteration":51,"passed_time":0.1021809911,"remaining_time":0.09432091484},
{"learn":[5.049834901],"iteration":52,"passed_time":0.1035096557,"remaining_time":0.0917915815},
{"learn":[5.03838627],"iteration":53,"passed_time":0.1046547378,"remaining_time":0.08915033219},
{"learn":[5.033534248],"iteration":54,"passed_time":0.1053839831,"remaining_time":0.08622325888},
{"learn":[5.023726885],"iteration":55,"passed_time":0.1065325934,"remaining_time":0.08370418053},
{"learn":[5.01290392],"iteration":56,"passed_time":0.1077048041,"remaining_time":0.08125099259},
{"learn":[5.005569127],"iteration":57,"passed_time":0.1088959037,"remaining_time":0.0788556544},
{"learn":[4.989969032],"iteration":58,"passed_time":0.1098757817,"remaining_time":0.07635435676},
{"learn":[4.976762446],"iteration":59,"passed_time":0.1109968981,"remaining_time":0.0739979321},
{"learn":[4.967222715],"iteration":60,"passed_time":0.1120926132,"remaining_time":0.07166576909},
{"learn":[4.954407599],"iteration":61,"passed_time":0.1140981774,"remaining_time":0.069931141},
{"learn":[4.942125056],"iteration":62,"passed_time":0.1152400711,"remaining_time":0.06768067668},
{"learn":[4.930230716],"iteration":63,"passed_time":0.1163228131,"remaining_time":0.06543158235},
{"learn":[4.921695642],"iteration":64,"passed_time":0.1176569966,"remaining_time":0.06335376741},
{"learn":[4.906405625],"iteration":65,"passed_time":0.118801495,"remaining_time":0.06120077017},
{"learn":[4.894330248],"iteration":66,"passed_time":0.1201565645,"remaining_time":0.05918159145},
{"learn":[4.88211557],"iteration":67,"passed_time":0.1212755773,"remaining_time":0.05707085989},
{"learn":[4.877946398],"iteration":68,"passed_time":0.1225384293,"remaining_time":0.05505349721},
{"learn":[4.863182126],"iteration":69,"passed_time":0.1238060009,"remaining_time":0.05305971466},
{"learn":[4.84646533],"iteration":70,"passed_time":0.124959122,"remaining_time":0.05103964137},
{"learn":[4.838014752],"iteration":71,"passed_time":0.1262105666,"remaining_time":0.04908188701},
{"learn":[4.82981137],"iteration":72,"passed_time":0.1273247608,"remaining_time":0.04709271975},
{"learn":[4.817094767],"iteration":73,"passed_time":0.1285540417,"remaining_time":0.04516763626},
{"learn":[4.808314151],"iteration":74,"passed_time":0.1297709138,"remaining_time":0.04325697128},
{"learn":[4.796235023],"iteration":75,"passed_time":0.1310603073,"remaining_time":0.04138746546},
{"learn":[4.784434534],"iteration":76,"passed_time":0.132326413,"remaining_time":0.03952607141},
{"learn":[4.774402487],"iteration":77,"passed_time":0.1335105029,"remaining_time":0.03765680851},
{"learn":[4.76731896],"iteration":78,"passed_time":0.1346182346,"remaining_time":0.03578459401},
{"learn":[4.75934113],"iteration":79,"passed_time":0.1357540374,"remaining_time":0.03393850935},
{"learn":[4.754106378],"iteration":80,"passed_time":0.1368331236,"remaining_time":0.03209665862},
{"learn":[4.744002932],"iteration":81,"passed_time":0.1379916233,"remaining_time":0.03029084414},
{"learn":[4.731700554],"iteration":82,"passed_time":0.1390938862,"remaining_time":0.02848910922},
{"learn":[4.723284153],"iteration":83,"passed_time":0.1404116598,"remaining_time":0.02674507806},
{"learn":[4.712232782],"iteration":84,"passed_time":0.141618473,"remaining_time":0.02499149524},
{"learn":[4.703046867],"iteration":85,"passed_time":0.1427494713,"remaining_time":0.02323828602},
{"learn":[4.698601855],"iteration":86,"passed_time":0.1443976101,"remaining_time":0.02157665438},
{"learn":[4.692429407],"iteration":87,"passed_time":0.1456154431,"remaining_time":0.01985665133},
{"learn":[4.675027364],"iteration":88,"passed_time":0.1466684112,"remaining_time":0.01812755644},
{"learn":[4.662368584],"iteration":89,"passed_time":0.1478450729,"remaining_time":0.01642723033},
{"learn":[4.646206172],"iteration":90,"passed_time":0.1489345107,"remaining_time":0.01472978677},
{"learn":[4.641245848],"iteration":91,"passed_time":0.1500721317,"remaining_time":0.01304975058},
{"learn":[4.633900435],"iteration":92,"passed_time":0.1511953711,"remaining_time":0.01138029675},
{"learn":[4.624738236],"iteration":93,"passed_time":0.1523661388,"remaining_time":0.009725498219},
{"learn":[4.612798287],"iteration":94,"passed_time":0.1535327412,"remaining_time":0.00808067059},
{"learn":[4.605222001],"iteration":95,"passed_time":0.1546183544,"remaining_time":0.006442431435},
{"learn":[4.601725912],"iteration":96,"passed_time":0.1558481604,"remaining_time":0.004820046199},
{"learn":[4.59722371],"iteration":97,"passed_time":0.157053905,"remaining_time":0.003205181735},
{"learn":[4.580235665],"iteration":98,"passed_time":0.1581442976,"remaining_time":0.001597417147},
{"learn":[4.57591791],"iteration":99,"passed_time":0.1592758017,"remaining_time":0}
]}